Workbook
Name Dep_Sch_Others: Conversion!$A$505:$D$543
Name Depreciation_Sch: Conversion!$A$396:$D$543
Name Int_Sch_other: Conversion!$A$545:$D$603
Name Interest_Sch: Conversion!$A$445:$D$502
Name Machine: Backup!$C$19:$I$60
Name Print_Changeover: Backup!$D$96:$F$108

Sheet Summary
A1: ="Country "&Input!C4 -> Country India | B1: ="Country "&Input!C5 -> Country INR | C1: ="Supplier "&Input!C6 -> Supplier
A2: ="Product "&Input!C2 -> Product Carton | B2: ="Period "&Input!C7 -> Period Nov25 | C2: PLM Code | D2: =Input!C3 -> xxxxxxxx
A3: =Input!A8 & " pcs" -> Annual Volume pcs | B3: =Input!C8 -> 3126950 | C3: ="Payment term "&Input!C117 & " Days" -> Payment term 60 Days
A4: Details | B4: =Input!$C$5&" /1000" -> INR /1000 | C4: EUR/1000 | D4: % Total Cost
A5: Material | B5: =B12 -> 888.61475 | C5: =B5/Input!$C$112 -> 8.5222476 | D5: =B5/$B$10 -> 0.60828173
A6: Conversion | B6: =B23 -> 363.64078 | C6: =B6/Input!$C$112 -> 3.4874919 | D6: =B6/$B$10 -> 0.24892232
A7: Margin | B7: =B33 -> 72.728157 | C7: =B7/Input!$C$112 -> 0.69749838 | D7: =B7/$B$10 -> 0.049784463
A8: Packaging | B8: =B36 -> 59.086333 | C8: =B8/Input!$C$112 -> 0.56666667 | D8: =B8/$B$10 -> 0.040446253
A9: Freight | B9: =B37 -> 76.790483 | C9: =B9/Input!$C$112 -> 0.73645807 | D9: =B9/$B$10 -> 0.05256524
A10: Total | B10: =SUM(B5:B9) -> 1460.8605 | C10: =SUM(C5:C9) -> 14.010363 | D10: =B10/$B$10 -> 1
A12: Material Cost | B12: =SUM(B13:B21) -> 888.61475 | C12: =SUM(C13:C21) -> 8.5222476 | D12: =B12/$B$10 -> 0.60828173
A13: =Input!C36&" "&Input!C37 -> 300 | B13: =Material!D23 -> 687.51679 | C13: =B13/Input!$C$112 -> 6.5936204 | D13: =B13/$B$10 -> 0.47062453
A14: Ink | B14: =Material!D30 -> 84.962816 | C14: =B14/Input!$C$112 -> 0.81483472 | D14: =B14/$B$10 -> 0.058159431
A15: =Input!C48 -> UV varnish (Gloss) | B15: =Material!D37 -> 79.65264 | C15: =B15/Input!$C$112 -> 0.76390755 | D15: =B15/$B$10 -> 0.054524467
A16: Hot Foil | B16: =Material!D80 -> 0 | C16: =B16/Input!$C$112 -> 0 | D16: =B16/$B$10 -> 0
A17: Window Carton | B17: =Material!D91 -> 0 | C17: =B17/Input!$C$112 -> 0
A18: Primer | B18: =Material!D52 -> 0 | C18: =B18/Input!$C$112 -> 0 | D18: =B18/$B$10 -> 0
A19: =Input!C53 -> Met Pet Film 12 micron | B19: =Material!D62+Material!D66 -> 0 | C19: =B19/Input!$C$112 -> 0 | D19: =B19/$B$10 -> 0
A20: Other Costs | B20: =Material!D97+Material!D98+Material!D99 -> 12.610428 | C20: =B20/Input!$C$112 -> 0.12094013 | D20: =B20/$B$10 -> 0.0086321915
A21: Wastage | B21: =Material!D55 -> 23.872075 | C21: =B21/Input!$C$112 -> 0.22894481 | D21: =B21/$B$10 -> 0.016341105
A23: Conversion Cost | B23: =SUM(B24:B31) -> 363.64078 | C23: =SUM(C24:C31) -> 3.4874919 | D23: =B23/$B$10 -> 0.24892232
A24: Electricity | B24: =Conversion!D252 -> 63.389963 | C24: =B24/Input!$C$112 -> 0.60794057 | D24: =B24/$B$10 -> 0.043392208
A25: Labour-Direct | B25: =Conversion!D254 -> 54.855507 | C25: =B25/Input!$C$112 -> 0.52609098 | D25: =B25/$B$10 -> 0.037550133
A26: Labour-Indirect | B26: =Conversion!E343 -> 58.551388 | C26: =B26/Input!$C$112 -> 0.56153628 | D26: =B26/$B$10 -> 0.040080068
A27: Repair & Maintenance | B27: =Conversion!D257 -> 11.015501 | C27: =B27/Input!$C$112 -> 0.10564401 | D27: =B27/$B$10 -> 0.0075404197
A28: Other Overheads | B28: =Conversion!D260 -> 11.015501 | C28: =B28/Input!$C$112 -> 0.10564401 | D28: =B28/$B$10 -> 0.0075404197
A29: Lease | B29: =Conversion!E342 -> 0 | C29: =B29/Input!$C$112 -> 0 | D29: =B29/$B$10 -> 0
A30: Depreciation | B30: =Conversion!D200+Conversion!E340 -> 67.835951 | C30: =B30/Input!$C$112 -> 0.65057975 | D30: =B30/$B$10 -> 0.046435611
A31: Interest | B31: =Conversion!D204+Conversion!E341+Conversion!D372 -> 96.976972 | C31: =B31/Input!$C$112 -> 0.93005631 | D31: =B31/$B$10 -> 0.066383458
A33: Margin | B33: =B23*Input!C98 -> 72.728157 | C33: =B33/Input!$C$112 -> 0.69749838 | D33: =B33/$B$10 -> 0.049784463
A35: Distribution | B35: =SUM(B36:B37) -> 135.87682 | C35: =SUM(C36:C37) -> 1.3031247 | D35: =B35/$B$10 -> 0.093011492
A36: Packaging | B36: =Conversion!D356 -> 59.086333 | C36: =B36/Input!$C$112 -> 0.56666667 | D36: =B36/$B$10 -> 0.040446253
A37: Freight | B37: =Conversion!D363 -> 76.790483 | C37: =B37/Input!$C$112 -> 0.73645807 | D37: =B37/$B$10 -> 0.05256524
A39: Process Costing | B39: =B4 -> INR /1000 | C39: =C4 -> EUR/1000 | D39: % Total Cost | E39: Material | F39: Energy | G39: Labour | H39: Repairs | I39: Other OH | J39: Lease | K39: Depreciation | L39: Interest | M39: Shipping | N39: Margin
A40: Feedstock | B40: =SUM(E40:N40) -> 722.46733 | C40: =B40/Input!$C$112 -> 6.9288129 | D40: =B40/$B$47 -> 0.49454915 | E40: =B13 -> 687.51679 | J40: =Conversion!J391 -> 0 | K40: =Conversion!J388+Conversion!J387 -> 22.009849 | L40: =Conversion!D372 -> 7.1155939 | N40: =SUM(F40:L40)*Input!$C$98 -> 5.8250885
A41: Printing | B41: =SUM(E41:N41) -> 352.11541 | C41: =B41/Input!$C$112 -> 3.376958 | D41: =B41/$B$47 -> 0.24103287 | E41: =B14+B15+Material!D97+Material!D55 -> 198.49121 | F41: =Conversion!D386 -> 31.635535 | G41: =Conversion!D384+Conversion!D385 -> 50.434955 | H41: =Conversion!D389 -> 3.2239668 | I41: =Conversion!D390 -> 3.2239668 | J41: =Conversion!D391 -> 0 | K41: =Conversion!D387+Conversion!D388 -> 13.201522 | L41: =Conversion!D392+Conversion!D393 -> 26.300219 | N41: =SUM(F41:L41)*Input!$C$98 -> 25.604033
A42: Folding & Gluing | B42: =SUM(E42:N42) -> 250.40096 | C42: =B42/Input!$C$112 -> 2.401467 | D42: =B42/$B$47 -> 0.17140648 | E42: =Material!D99+Material!D98 -> 2.60675 | F42: =Conversion!H386+Conversion!I386 -> 31.754428 | G42: =Conversion!H384+Conversion!H385+Conversion!I384+Conversion!I385 -> 62.971939 | H42: =Conversion!H389+Conversion!I389 -> 7.7915345 | I42: =Conversion!H390+Conversion!I390 -> 7.7915345 | J42: =Conversion!H391+Conversion!I391 -> 0 | K42: =Conversion!H387+Conversion!I387+Conversion!H388+Conversion!I388 -> 32.62458 | L42: =Conversion!H392+Conversion!H393+Conversion!I392+Conversion!I393 -> 63.561159 | N42: =SUM(F42:L42)*Input!$C$98 -> 41.299035
A43: Lamination | B43: =SUM(E43:N43) -> 0 | C43: =B43/Input!$C$112 -> 0 | D43: =B43/$B$47 -> 0 | E43: =B18+B19 -> 0 | F43: =Conversion!G386 -> 0 | G43: =Conversion!G384+Conversion!G385 -> 0 | H43: =Conversion!G389 -> 0 | I43: =Conversion!G390 -> 0 | J43: =Conversion!G391 -> 0 | K43: =Conversion!G387+Conversion!G388 -> 0 | L43: =Conversion!G392+Conversion!G393 -> 0 | N43: =SUM(F43:L43)*Input!$C$98 -> 0
A44: Foil Stamping & other decoration | B44: =SUM(E44:N44) -> 0 | C44: =B44/Input!$C$112 -> 0 | D44: =B44/$B$47 -> 0 | E44: =B16+B17 -> 0 | F44: =Conversion!F386+Conversion!E386 -> 0 | G44: =Conversion!E384+Conversion!E385+Conversion!F384+Conversion!F385 -> 0 | H44: =Conversion!F389+Conversion!E389 -> 0 | I44: =Conversion!F390+Conversion!E390 -> 0 | J44: =Conversion!F391+Conversion!E391 -> 0 | K44: =Conversion!F387+Conversion!E387+Conversion!F388+Conversion!E388 -> 0 | L44: =Conversion!F392+Conversion!F393+Conversion!E392+Conversion!E393 -> 0 | N44: =SUM(F44:L44)*Input!$C$98 -> 0
A45: Dispatch | B45: =SUM(E45:N45) -> 135.87682 | C45: =B45/Input!$C$112 -> 1.3031247 | D45: =B45/$B$47 -> 0.093011492 | M45: =B35 -> 135.87682 | N45: =SUM(F45:L45)*Input!$C$98 -> 0
A47: Total Cost | B47: =SUM(B40:B45) -> 1460.8605 | C47: =SUM(C40:C45) -> 14.010363 | D47: =B47/$B$47 -> 1 | E47: =SUM(E40:E46) -> 888.61475 | F47: =SUM(F40:F46) -> 63.389963 | G47: =SUM(G40:G46) -> 113.40689 | H47: =SUM(H40:H46) -> 11.015501 | I47: =SUM(I40:I46) -> 11.015501 | J47: =SUM(J40:J46) -> 0 | K47: =SUM(K40:K46) -> 67.835951 | L47: =SUM(L40:L46) -> 96.976972 | ... N47: =SUM(N40:N46) -> 72.728157
B48: =B10-B47 -> 0 | C48: =C10-C47 -> 0 | E48: =B5-E47 -> 0 | F48: =B24-F47 -> 0 | G48: =B25+B26-G47 -> 0 | H48: =B27-H47 -> 0 | I48: =B28-I47 -> 0 | J48: =B29-J47 -> 0 | K48: =B30-K47 -> 0 | L48: =B31-L47 -> 0 | M48: =B35-M47 -> 0 | N48: =B33-N47 -> 0

Sheet Input
D1: Note | E1: Mandatory field
A2: Product | C2: Carton
A3: PLM Code | C3: xxxxxxxx
A4: Country | C4: India
A5: Currency Symbol | C5: =VLOOKUP($C$4,_xlnm.Database,MATCH($A5,Database!$A$10:$P$10,0),0) -> INR
A6: Supplier
A7: Costing Period | C7: Nov25
A8: Annual Volume | C8: 3126950
A9: Average order size | C9: =C8/12 -> 260579.17
A10: SKU Code | C10: xxxx
A11: SKU Description
A13: Material Rates | C13: ="Rate "&C5 -> Rate INR
A14: Board Rate | B14: Per kg | C14: 45
A15: Ink Rate | B15: Per kg | C15: =IF(D15=0,VLOOKUP($C$4,_xlnm.Database,MATCH($A15,Database!$A$10:$U$10,0),0),D15) -> 834.16 | E15: * User may input as required
A16: Varnish Rate | B16: Per kg | C16: =IF(D16=0,VLOOKUP($C$4,_xlnm.Database,MATCH($A16,Database!$A$10:$U$10,0),0),D16) -> 521.35 | E16: * User may input as required
A17: Foil Rate | B17: Per Roll | C17: =IF(D17=0,VLOOKUP($C$4,_xlnm.Database,MATCH($A17,Database!$A$10:$U$10,0),0),D17) -> 938.43 | E17: * User may input as required
A18: Film Rate | B18: Per kg | C18: =IF(D18=0,VLOOKUP($C$4,_xlnm.Database,MATCH($A18,Database!$A$10:$U$10,0),0),D18) -> 208.54 | E18: * User may input as required
A19: Primer Rate | B19: Per kg | C19: =IF(D19=0,VLOOKUP($C$4,_xlnm.Database,MATCH($A19,Database!$A$10:$U$10,0),0),D19) -> 208.54 | E19: * User may input as required
A21: Carton Details
A22: No of Colours | B22: Nos | C22: 5
A23: Common Colours | B23: Nos | C23: 2
A24: No of Designs | B24: Nos | C24: 1
A25: No of Print Runs / year | B25: Nos | C25: 12
A26: No of Designs/Run | B26: Nos | C26: =C24 -> 1
A27: Length 1 | B27: mm | C27: 36.3
A28: Length 2 | B28: mm | C28: 37
A29: Width 1 | B29: mm | C29: 46
A30: Width 2 | B30: mm | C30: 46
A31: Height | B31: mm | C31: 179
A32: Max Flap | B32: mm | C32: =275.9-179 -> 96.9
A33: Gluing Area | B33: mm | C33: 13
A34: Machine Size | C34: IIIB | D34: * Please select from Drop down list
A35: Grain Direction | C35: Long | D35: * Please select from Drop down list
A36: Board Type
A37: Board GSM | B37: GSM | C37: 300
A38: Interlock | C38: N | D38: * Please select from Drop down list
A39: Interlock Value | B39: mm | D39: =IF($C$38="N"," ","Dimensions Required")
A41: Decoration
A42: Spot Varnish | C42: N | D42: * Please select from Drop down list
A43: Hot Foiling | C43: N | D43: * Please select from Drop down list
A44: Lamination | C44: N | D44: * Please select from Drop down list
A45: Window Carton | C45: N | D45: * Please select from Drop down list
A47: Decoration Details
A48: Varnish Type | C48: UV varnish (Gloss) | D48: * Please select from Drop down list
A49: Spot Varnish Type | C49: UV Varnish (Gloss)
A50: Spot Varnish Area (% of Total SQM) | C50: 0.3 | D50: =IF($C$42="N"," ","* Please input % of Area Coverage")
A51: Foil Length | B51: mm | C51: =C27*40% -> 14.52 | D51: =IF($C$43="N"," ","Dimensions Required")
A52: Foil Width | B52: mm | C52: =C31*40% -> 71.6 | D52: =IF($C$43="N"," ","Dimensions Required")
A53: Film Type | C53: Met Pet Film 12 micron | D53: * Please input the Film
A54: Film micron | B54: micron | C54: 10 | D54: =IF($C$44="N"," ","Dimensions Required")
A55: Film GSM | B55: GSM | C55: =C54*1.4 -> 14
A56: Primer | C56: UV Primer | D56: * Please select from Drop down list
A57: Window - Width | B57: mm | C57: =179/2 -> 89.5 | D57: =IF($C$45="N"," ","Dimensions Required")
A58: Window - Length | B58: mm | C58: =46+37 -> 83 | D58: =IF($C$45="N"," ","Dimensions Required")
A59: Window Film micron | B59: micron | C59: 125 | D59: =IF($C$45="N"," ","Dimensions Required")
A60: Window Film GSM | B60: GSM | C60: =C59*1.4 -> 175
A62: Machine Details
A63: Printing Machine | C63: KBA 8000 | D63: * Please select from Drop down list
A64: Spot Varnish Machine | C64: Unison | D64: * Please select from Drop down list
A65: Hot Foiling Machine | C65: Hot Foil Machine | D65: * Please select from Drop down list
A66: Lamination Machine | C66: Kompac KwikPrint / EZ Koat | D66: * Please select from Drop down list
A67: Creasing & Blanking Machine | C67: Bobst Mastercut | D67: * Please select from Drop down list
A68: Folder - Gluer Machine | C68: Bobst Masterfold | D68: * Please select from Drop down list
A69: Window Patching Machine | C69: =Backup!C58 -> Medium automatic window patcher | D69: * Please select from Drop down list
A71: Energy
A72: Electricity | B72: =$C$5&" /KWH" -> INR /KWH | C72: =IF(D72=0,VLOOKUP($C$4,_xlnm.Database,MATCH($A72,Database!$A$10:$P$10,0),0),D72) -> 10.72 | E72: * User may input as required
A74: Manpower Cost
A75: Skilled Labour | B75: =$C$5&" /Annum" -> INR /Annum | C75: =IF(D75=0,VLOOKUP($C$4,_xlnm.Database,MATCH($A75,Database!$A$10:$P$10,0),0),D75) -> 541800 | E75: * User may input as required
A76: Engineer | B76: =$C$5&" /Annum" -> INR /Annum | C76: =IF(D76=0,VLOOKUP($C$4,_xlnm.Database,MATCH($A76,Database!$A$10:$P$10,0),0),D76) -> 1260000 | E76: * User may input as required
A77: Production Manager | B77: =$C$5&" /Annum" -> INR /Annum | C77: =IF(D77=0,VLOOKUP($C$4,_xlnm.Database,MATCH($A77,Database!$A$10:$P$10,0),0),D77) -> 1890000 | E77: * User may input as required
A78: No of Shifts | C78: 3
A80: Overheads
A81: Repair & Maintenance | B81: Machine Value | C81: 0.02
A82: Other Overheads | B82: Machine Value | C82: 0.02
A84: Depreciation Assumption
A85: Depreciation | B85: % | C85: =IF(D85=0,VLOOKUP($C$4,_xlnm.Database,MATCH($A85,Database!$A$10:$P$10,0),0),D85) -> 0.15 | E85: * User may input as required
A86: Completed Life of Asset | B86: Years | C86: 5
A87: Depreciation on Building | B87: % | C87: =IF(D87=0,VLOOKUP($C$4,_xlnm.Database,MATCH($A87,Database!$A$10:$P$10,0),0),D87) -> 0.1 | E87: * User may input as required
A89: Premises
A90: Land Cost | B90: INR Per Sq Mtr | C90: =IF(D90=0,VLOOKUP($C$4,_xlnm.Database,MATCH($A90,Database!$A$10:$P$10,0),0),D90) -> 14833.58 | E90: * User may input as required
A91: Building Cost | B91: INR Per Sq Mtr | C91: =IF(D91=0,VLOOKUP($C$4,_xlnm.Database,MATCH($A91,Database!$A$10:$P$10,0),0),D91) -> 36681.16 | E91: * User may input as required
A92: Lease Cost | B92: INR Per Sq Mtr | C92: =IF(D92=0,VLOOKUP($C$4,_xlnm.Database,MATCH($A92,Database!$A$10:$P$10,0),0),D92) -> 1560.6 | E92: * User may input as required
A93: Type of Premises | C93: Owned | D93: * Please select from Drop down list
A95: Financials
A96: Interest on Long Term Loan | B96: % | C96: =IF(D96=0,VLOOKUP($C$4,_xlnm.Database,MATCH($A96,Database!$A$10:$P$10,0),0),D96) -> 0.125 | E96: * User may input as required
A97: Interest on Working Capital | B97: % | C97: =IF(D97=0,VLOOKUP($C$4,_xlnm.Database,MATCH($A97,Database!$A$10:$P$10,0),0),D97) -> 0.14 | E97: * User may input as required
A98: Margin | B98: % | C98: 0.2
A99: LT Debt - Equity Ratio | B99: % | C99: 0.7
A101: Packing
A102: Cartons Per Box | B102: Nos | C102: 1500
A103: Boxes Per Pallet | B103: Nos | C103: 0
A104: Boxes Per Container | B104: Nos | C104: =IF(C9/C102>300,300,C9/C102) -> 173.71944
A106: Logistics
A107: Container Type | C107: 22 Feet Container
A108: Weight per container | B108: kg | C108: 13000
A109: Freight Cost | B109: =$C$5&"/ Container" -> INR/ Container | C109: =230*C113 -> 20010
A111: Exchange Rates
A112: Euro | B112: =$C$5 -> INR | C112: =IF(D112=0,VLOOKUP($C$4,_xlnm.Database,MATCH($A112,Database!$A$10:$P$10,0),0),D112) -> 104.27 | E112: * User may input as required
A113: USD | B113: =$C$5 -> INR | C113: =IF(D113=0,VLOOKUP($C$4,_xlnm.Database,MATCH($A113,Database!$A$10:$P$10,0),0),D113) -> 87 | E113: * User may input as required
A115: Payment Terms
...

Sheet Material
D3: 1
B4: SKU Code | C4: Unit | D4: =_xlfn.XLOOKUP($B4,Input!A:A,Input!C:C,0) -> xxxx
B5: SKU Description | D5: =_xlfn.XLOOKUP($B5,Input!A:A,Input!C:C,0) -> 0
B6: Flat Size
B7: Length | C7: mm | D7: =_xlfn.XLOOKUP($B7,Conversion!B:B,Conversion!D:D,0) -> 178.3
B8: Width | C8: mm | D8: =_xlfn.XLOOKUP($B8,Conversion!B:B,Conversion!D:D,0) -> 275.9
B9: Area of 1 carton | C9: Sq. Mtrs | D9: =D7*D8/10^6 -> 0.04919297
B11: Actual Sheet Size to use
B12: Sheet Length | C12: mm | D12: =_xlfn.XLOOKUP($B12,Conversion!B:B,Conversion!D:D,0) -> 906.5
B13: Sheet Width | C13: mm | D13: =_xlfn.XLOOKUP($B13,Conversion!B:B,Conversion!D:D,0) -> 561.8
B14: Area of Sheet Used | C14: Sq. Mtrs | D14: =D12*D13/10^6 -> 0.5092717
B16: No of Ups per Sheet | C16: Nos | D16: =_xlfn.XLOOKUP($B16,Conversion!B:B,Conversion!D:D,0) -> 10
B18: BOARD
B19: Board Type | D19: =_xlfn.XLOOKUP($B19,Input!A:A,Input!C:C,0) -> 0
B20: Board GSM | C20: GSM | D20: =_xlfn.XLOOKUP($B20,Input!A:A,Input!C:C,0) -> 300
B21: Board Consumption | C21: Kg | D21: =D14*(D20/1000)/(D16/1000) -> 15.278151
B22: Board Rate | C22: =Input!$C$5& " /Kg" -> INR /Kg | D22: =_xlfn.XLOOKUP($B22,Input!A:A,Input!C:C,0) -> 45
A23: Material Cost | B23: Board Cost | C23: =Input!$C$5&"/1000 Cartons" -> INR/1000 Cartons | D23: =D21*D22 -> 687.51679
B25: Ink
B26: Ink Type | D26: Offset Ink
B27: Ink Rate | C27: =Input!$C$5& " /Kg" -> INR /Kg | D27: =_xlfn.XLOOKUP($B27,Input!A:A,Input!C:C,0) -> 834.16
B28: Ink GSM | C28: GSM | D28: 2
B29: Ink Consumption | C29: Kg/1000 Cartons | D29: =D28*($D$14/1000)/($D$16/1000) -> 0.10185434
A30: Material Cost | B30: Ink Cost | C30: =Input!$C$5&"/1000 Carton" -> INR/1000 Carton | D30: =D27*D29 -> 84.962816
B32: Varnish
B33: Varnish Type | D33: =_xlfn.XLOOKUP($B33,Input!A:A,Input!C:C,0) -> UV varnish (Gloss)
B34: Varnish Rate | C34: =Input!$C$5& " /Kg" -> INR /Kg | D34: =_xlfn.XLOOKUP($B34,Input!A:A,Input!C:C,0) -> 521.35
B35: Varnish GSM | C35: GSM | D35: 3
B36: Varnish Consumption | C36: Kg/1000 Cartons | D36: =D35*($D$14/1000)/($D$16/1000) -> 0.15278151
A37: Material Cost | B37: Varnish Cost | C37: =Input!$C$5&"/1000Cartons" -> INR/1000Cartons | D37: =D34*D36 -> 79.65264
B39: Spot Varnish | D39: =Input!$C$42 -> N
B40: Varnish Type | D40: =_xlfn.XLOOKUP($B40,Input!A:A,Input!C:C,0) -> UV varnish (Gloss)
B41: Varnish Rate | C41: =Input!$C$5& " /Kg" -> INR /Kg | D41: =_xlfn.XLOOKUP($B41,Input!A:A,Input!C:C,0) -> 521.35
B42: Varnish GSM | C42: GSM | D42: 3
B43: Spot Varnish Area (% of Total SQM) | C43: % | D43: =_xlfn.XLOOKUP($B43,Input!A:A,Input!C:C,0) -> 0.3
B44: Varnish Consumption | C44: Kg/1000 Cartons | D44: =D42*($D$14/1000)/($D$16/1000)*D43 -> 0.045834453
A45: Material Cost | B45: Varnish Cost | C45: =Input!$C$5&"/1000Cartons" -> INR/1000Cartons | D45: =IF(D39="N",0,D41*D44) -> 0
B48: Primer | D48: =D57 -> N
B49: Primer Rate | C49: =Input!$C$5& " /Kg" -> INR /Kg | D49: =_xlfn.XLOOKUP($B49,Input!A:A,Input!C:C,0) -> 208.54
B50: Primer GSM | C50: GSM | D50: 2
B51: Primer Consumption | C51: Kg/1000 Cartons | D51: =D50*($D$14/1000)/($D$16/1000) -> 0.10185434
A52: Material Cost | B52: Primer Cost | C52: =Input!$C$5&"/1000Cartons" -> INR/1000Cartons | D52: =IF(D48="N",0,D49*D51) -> 0
B54: Wastage | C54: % | D54: =Conversion!D84 -> 0.028014519
A55: Material Cost | B55: Wastage | C55: =Input!$C$5&"/1000Cartons" -> INR/1000Cartons | D55: =SUM(D23+D30+D37+D52+D45)*D54 -> 23.872075
B57: LAMINATION | D57: =Input!$C$44 -> N
B58: Film Type | D58: =_xlfn.XLOOKUP($B58,Input!A:A,Input!C:C,0) -> Met Pet Film 12 micron
B59: Film Rate | C59: =Input!$C$5& " /Kg" -> INR /Kg | D59: =_xlfn.XLOOKUP($B59,Input!A:A,Input!C:C,0) -> 208.54
B60: Film GSM | C60: GSM | D60: =_xlfn.XLOOKUP(B60,Input!$A:$A,Input!$C:$C,0) -> 14
B61: Film Consumption | C61: Kg/1000 Cartons | D61: =D60*($D$14/1000)/($D$16/1000) -> 0.71298038
A62: Material Cost | B62: Film Cost | C62: =Input!$C$5&"/1000Cartons" -> INR/1000Cartons | D62: =IF($D$57="N",0,D59*D61) -> 0
B63: Adhesive Rate | C63: Kg/1000 Cartons | D63: =1.7*Input!$C$113 -> 147.9
B64: Adhesive Specs | C64: GSM | D64: =5 -> 5
B65: Adhesive Consumption | C65: Kg/1000 Cartons | D65: =D64*($D$14/1000)/($D$16/1000) -> 0.25463585
A66: Material Cost | B66: Adhesive Cost | C66: =Input!$C$5&"/1000Cartons" -> INR/1000Cartons | D66: =IF(D57="N",0,D63*D65) -> 0
B68: Wastage | C68: % | D68: =Conversion!D140 -> 0
A69: Material Cost | B69: Wastage | C69: =Input!$C$5&"/1000Cartons" -> INR/1000Cartons | D69: =(SUM($D$23+$D$30+$D$37+$D$52+$D$45)+SUM($D$62+$D$66))*D68 -> 0
B71: FOIL STAMPING | D71: =Input!$C$43 -> N
B72: Roll - Width | C72: mm | D72: 610
B73: Roll - Length | C73: mm | D73: 120000
B74: Foil Length | C74: mm | D74: =_xlfn.XLOOKUP($B74,Input!A:A,Input!C:C,0) -> 14.52
B75: Foil Width | C75: mm | D75: =_xlfn.XLOOKUP($B75,Input!A:A,Input!C:C,0) -> 71.6
B76: Foil Consumption per carton | C76: Sq Inch | D76: =D74*D75/(100*2.54*2.54) -> 1.6114328
B77: No of Cartons per Roll | C77: Nos | D77: =IF(D76=0,0,(D72*D73)/(D74*D75)) -> 70409.53
B78: Foil Type | D78: Hot Foil - Silver
B79: Foil Rate | C79: Per Roll | D79: =_xlfn.XLOOKUP($B79,Input!A:A,Input!C:C,0) -> 938.43
A80: Material Cost | B80: Foil Cost | C80: =Input!$C$5&"/1000Cartons" -> INR/1000Cartons | D80: =IF(D71="N",0,D79/D77)*1000 -> 0
B82: Wastage | C82: % | D82: =Conversion!D120 -> 0
A83: Material Cost | B83: Wastage | C83: =Input!$C$5&"/1000Cartons" -> INR/1000Cartons | D83: =(SUM($D$23+$D$30+$D$37+$D$52+$D$45)+SUM($D$62+$D$66))*D82 -> 0
B85: =Input!A45 -> Window Carton | D85: =Input!$C$45 -> N
B86: Window - Width | C86: mm | D86: =_xlfn.XLOOKUP($B86,Input!A:A,Input!C:C,0) -> 89.5
B87: Window - Length | C87: mm | D87: =_xlfn.XLOOKUP($B87,Input!A:A,Input!C:C,0) -> 83
B88: Area of 1 carton | C88: Sq. Mtrs | D88: =(D86*D87)/10^6 -> 0.0074285
B89: Window Film GSM | C89: GSM | D89: =_xlfn.XLOOKUP($B89,Input!A:A,Input!C:C,0) -> 175
B90: Film Rate | C90: Per Kg | D90: =_xlfn.XLOOKUP($B90,Input!A:A,Input!C:C,0) -> 208.54
A91: Material Cost | B91: Film Cost | C91: =Input!$C$5&"/1000Cartons" -> INR/1000Cartons | D91: =IF(D85="N",0,(D89*D90*D88)) -> 0
B94: Wastage | C94: % | D94: =Conversion!D120 -> 0
A95: Material Cost | B95: Wastage | C95: =Input!$C$5&"/1000Cartons" -> INR/1000Cartons | D95: =(SUM($D$23+$D$30+$D$37+$D$52+$D$45)+SUM($D$62+$D$66))*D94 -> 0
A97: Material Cost | B97: Printing Plate Cost | C97: =Input!$C$5&"/1000Cartons" -> INR/1000Cartons | D97: =Conversion!D96 -> 10.003678
A98: Material Cost | B98: Hot Foil Die Cost | C98: =Input!$C$5&"/1000Cartons" -> INR/1000Cartons | D98: =Conversion!D132 -> 0
A99: Material Cost | B99: Creasing & Blanking Die Cost | C99: =Input!$C$5&"/1000Cartons" -> INR/1000Cartons | D99: =Conversion!D180 -> 2.60675
B101: Total Wastage | C101: % | D101: =D102/D104 -> 0.026864369
B102: Total Wastage | C102: =Input!$C$5&"/1000Cartons" -> INR/1000Cartons | D102: =(D55+D69+D83+D95) -> 23.872075
B104: Material Cost | C104: =Input!$C$5&"/1000Cartons" -> INR/1000Cartons | D104: =SUMIF(A23:A102,B104,D23:D102) -> 888.61475

Sheet Conversion
B2: Efficiency | C2: 0.8
B3: No of Hours | C3: 24
B4: No of Working Days | C4: 330
B5: No of Working Hours | C5: =C3*C4 -> 7920
D6: 1
B7: SKU Code | C7: Unit | D7: =_xlfn.XLOOKUP($B7,Input!A:A,Input!C:C,0) -> xxxx
B8: SKU Description | D8: =_xlfn.XLOOKUP($B8,Input!A:A,Input!C:C,0) -> 0
B9: Printing
B10: Machine Type | D10: Offset
B11: Printing Machine | D11: =_xlfn.XLOOKUP(B11,Input!$A:$A,Input!$C:$C,0) -> KBA 8000
B12: Machine Size | C12: Flexo Printing Machine | D12: =_xlfn.XLOOKUP($B12,Input!A:A,Input!C:C,0) -> IIIB
B14: Max Size Usable on Machine
B15: Max width | C15: mm | D15: =VLOOKUP($D$12,Backup!$B$116:$D$120,MATCH(Conversion!$B15,Backup!$B$116:$D$116,0),0) -> 1020
B16: Max length | C16: mm | D16: =VLOOKUP($D$12,Backup!$B$116:$D$120,MATCH(Conversion!$B16,Backup!$B$116:$D$116,0),0) -> 720
B18: Carton Specs
B19: Length 1 | C19: mm | D19: =_xlfn.XLOOKUP($B19,Input!A:A,Input!C:C,0) -> 36.3
B20: Length 2 | C20: mm | D20: =_xlfn.XLOOKUP($B20,Input!A:A,Input!C:C,0) -> 37
B21: Width 1 | C21: mm | D21: =_xlfn.XLOOKUP($B21,Input!A:A,Input!C:C,0) -> 46
A22: Area of 1 carton | B22: Width 2 | C22: mm | D22: =_xlfn.XLOOKUP($B22,Input!A:A,Input!C:C,0) -> 46
B23: Height | C23: mm | D23: =_xlfn.XLOOKUP($B23,Input!A:A,Input!C:C,0) -> 179
B24: Max Flap | C24: mm | D24: =_xlfn.XLOOKUP($B24,Input!A:A,Input!C:C,0) -> 96.9
B25: Gluing Area | C25: mm | D25: =_xlfn.XLOOKUP($B25,Input!A:A,Input!C:C,0) -> 13
B27: Flat Size
B28: Length | C28: mm | D28: =D19+D20+D21+D22+D25 -> 178.3
B29: Width | C29: mm | D29: =D23+D24 -> 275.9
B30: Area of 1 Carton | C30: Sqm | D30: =D28*D29/10^6 -> 0.04919297
B32: Grain Direction | D32: =_xlfn.XLOOKUP($B32,Input!A:A,Input!C:C,0) -> Long
B34: LAYOUT (Sheet Margins)
B35: Side Lay-1 | C35: mm | D35: 5
B36: Side Lay-2 | C36: mm | D36: 5
B37: Gripper Margin | C37: mm | D37: 10
B38: Back Lay | C38: mm | D38: 5
B39: Trimmer | C39: mm | D39: 0
B40: Double cut margin | C40: mm | D40: 0
B41: Gutter | C41: mm | D41: 0
B42: Interlock Value | C42: mm | D42: =_xlfn.XLOOKUP($B42,Input!A:A,Input!C:C,0) -> 0
B44: No of Ups
B45: Lengthwise | C45: Nos | D45: =ROUNDDOWN(IF($D32="Long",$D15/$D28,IF($D32="Short",$D15/$D28,0)),0) -> 5
B46: Widthwise | C46: Nos | D46: =ROUNDDOWN(IF($D32="Long",$D16/$D29,IF($D32="Short",$D16/$D29,0)),0) -> 2
A47: No of Ups per Sheet | B47: No of Ups per sheet | C47: Nos | D47: =D45*D46 -> 10
B49: Actual Sheet Size to Use
B50: Sheet Length | C50: mm | D50: =D28*D45+D37+D38 -> 906.5
B51: Sheet Width | C51: mm | D51: =D29*D46+D35+D36-D42 -> 561.8
A52: Area of Sheet Used | B52: Area of Sheet | C52: SQM | D52: =D50*D51/10^6 -> 0.5092717
B54: Line Speed | C54: Sheets/hour | D54: =VLOOKUP(D11,Machine,COLUMNS(Backup!$C$19:$E$19),0) -> 12000
B55: No of Colours | C55: Nos | D55: =_xlfn.XLOOKUP($B55,Input!A:A,Input!C:C,0) -> 5
B56: No of Designs | C56: Nos | D56: =_xlfn.XLOOKUP($B56,Input!A:A,Input!C:C,0) -> 1
B57: Common Colours | C57: Nos | D57: =_xlfn.XLOOKUP($B57,Input!A:A,Input!C:C,0) -> 2
B58: Design Change Colours | C58: Nos | D58: =D55-D57 -> 3
B59: No of Print Runs / year | C59: Nos | D59: =_xlfn.XLOOKUP($B59,Input!A:A,Input!C:C,0) -> 12
B60: No of Designs/Run | C60: Nos | D60: =_xlfn.XLOOKUP($B60,Input!A:A,Input!C:C,0) -> 1
B61: Annual Volume | C61: Nos | D61: =_xlfn.XLOOKUP($B61,Input!A:A,Input!C:C,0) -> 3126950
B62: Average Order Size | C62: Nos | D62: =D61/D59 -> 260579.17
B63: No of Plate changes | C63: Nos | D63: =D55 -> 5
B64: Average Run Size | C64: No of Sheets | D64: =D62/D47 -> 26057.917
B65: Machine Utilised | C65: Hours | D65: =D64/(D54*C$2)*D59 -> 32.572396
B67: Set Up
B68: No of Set Ups/Year | C68: Nos | D68: =D59*D60 -> 12
B69: Time Required for Set Up | C69: Min | D69: =VLOOKUP($D$10&$D$55,Print_Changeover,COLUMNS(Backup!$D$96:$E$96),0) -> 45
B70: Machine Speed at Set up | C70: Sheets/Min | D70: =(D54*5%)/60 -> 10
B71: No of Sheets Wasted at Set up | C71: Nos | D71: =D69*D70 -> 450
B72: Set Up Wastage | C72: % | D72: =D71/D64 -> 0.017269224
B73: Machine Utilised | C73: Hours | D73: =D71/(D70*C$2)/60*D68 -> 11.25
B75: Registration
B76: No of Registrations/Year | C76: Nos | D76: =$D$68 -> 12
B77: Time Required for Registration | C77: Min | D77: =VLOOKUP($D$10&$D$58,Print_Changeover,COLUMNS(Backup!$D$96:$F$96),0) -> 14
B78: Machine Speed at Registration | C78: Sheets/Min | D78: =(D54*10%)/60 -> 20
B79: No of Sheets Wasted at Registration | C79: Nos | D79: =D77*D78 -> 280
B80: Resgistration Wastage | C80: % | D80: =D79/D64 -> 0.010745295
B81: Design Change Wastage | C81: % | D81: =D77*D78/D64*(D60-1) -> 0
B82: Machine Utilised | C82: Hours | D82: =D79/(D78*C$2)/60*D76 -> 3.5
A84: Total Wastage | B84: Total Printing Wastage | C84: % | D84: =D72+D80+D81 -> 0.028014519
B86: No of Hours Utilised | C86: Hours | D86: =D65+D73+D82 -> 47.322396
B87: No of Machines Required | C87: Nos | D87: =D86/$C$5 -> 0.00597505
B89: Plate Cost
B90: No of Print Runs/Year | C90: Nos | D90: =$D$68 -> 12
B91: Average Run Size | C91: Nos of Sheets | D91: =D64 -> 26057.917
B92: No of Colours | C92: Nos | D92: =D55 -> 5
B93: No of Plates | C93: Nos | D93: =D92 -> 5
B94: Ink Plate Cost | C94: =Input!C5&" /Pc" -> INR /Pc | D94: =_xlfn.XLOOKUP(B94,Backup!B:B,Backup!F:F) -> 521.35
B95: Total Plate Cost | C95: =Input!C5 -> INR | D95: =D93*D94 -> 2606.75
B96: Plate Cost | C96: Per 1000 Carton | D96: =D95*1000/(D91*D47) -> 10.003678
B98: Spot Varnish | D98: =_xlfn.XLOOKUP($B98,Input!A:A,Input!C:C,0) -> N
B99: Spot Varnish Machine | D99: =_xlfn.XLOOKUP(B99,Input!$A:$A,Input!$C:$C,0) -> Unison
B100: Varnish GSM | C100: Gsm | D100: 2
B101: No of Set Ups/Year | C101: Nos | D101: =$D$68 -> 12
B102: Time Required for Set Up | C102: Min | D102: 30
A103: Energy - Cup | B103: Machine Speed at Set up | C103: Sheets/Hour | D103: =VLOOKUP($D$99,Machine,COLUMNS(Backup!$C$19:$E$19),0)*25% -> 1250
B104: No of Sheets Wasted at Set up | C104: Nos | D104: =D102*D103/60 -> 625
A105: Total Wastage | B105: Set Up Wastage | C105: % | D105: =IF(D98="N",0,D104/D64) -> 0
B106: Machine Set Up Utilised | C106: Hours | D106: =IF(D98="N",0,D104/(D102*C$2)/60*D101) -> 0
B107: Machine Speed | C107: Sheets/Hour | D107: =VLOOKUP($D$99,Machine,COLUMNS(Backup!$C$19:$E$19),0) -> 5000
B108: Machine Run On Utilised | C108: Hours | D108: =IF(D98="N",0,D91/(D107*C$2))*D101 -> 0
B110: Total Machine Run Utilised | C110: Hours | D110: =D106+D108 -> 0
B111: No of Machines Required | D111: =D110/$C$5 -> 0
B113: Hot Foiling | D113: =_xlfn.XLOOKUP($B113,Input!A:A,Input!C:C,0) -> N
B114: Hot Foiling Machine | D114: =_xlfn.XLOOKUP(B114,Input!$A:$A,Input!$C:$C,0) -> Hot Foil Machine
B115: Foil GSM | C115: Gsm | D115: 2
B116: No of Set Ups/Year | C116: Nos | D116: =$D$68 -> 12
B117: Time Required for Set Up | C117: Min | D117: 30
...

Sheet Database
D1: Labour Annual salaries (CTC) | G1: Utilities | H1: Rates
A2: Country | B2: Currency | C2: Currency Symbol | D2: Manager | E2: Supervisor | F2: Operator | G2: Electricity Rate (per kWh) | H2: Borrowing rate (%) | J2: Exchange rate with Euro | K2: Exchange rate with USD | L2: Land Cost per Sq Mt | M2: Building Cost per Sq Mt | N2: Lease Cost per Sq Mt
A3: Vietnam | B3: Vietnamese Dong | C3: VND
A4: Philippines | B4: Philippines Pesos | C4: PHP
A5: China | B5: Chinese Yuan | C5: CNY
W6: INR | X6: 15000
D9: kWH | E9: Manpower Cost | J9: per sqm | K9: per sqm | L9: per sqm | O9: Exchange rate with Euro | P9: Exchange rate with USD | W9: KM | X9: 300
A10: Country | B10: Currency | C10: Currency Symbol | D10: Electricity | E10: Skilled Labour | F10: Engineer | G10: Production Manager | H10: Depreciation | I10: Depreciation on Building | J10: Land Cost | K10: Building Cost | L10: Lease Cost | M10: Interest on Long Term Loan | N10: Interest on Working Capital | O10: Euro | P10: USD | Q10: Ink Rate | R10: Varnish Rate | S10: Foil Rate | T10: Film Rate | U10: Primer Rate | W10: =X6/X9 -> 50
A11: Argentina | B11: Argentinian Pesos | C11: ARS | D11: 129.15 | H11: 0.1 | I11: 0.02 | O11: 1684.16 | P11: 1451.24
A12: Brazil | B12: Brazilian Reals | C12: BRL | D12: 0.657 | H12: 0.1 | I12: 0.04 | O12: 6.23 | P12: 5.37
A13: China | B13: Chinese Yuan | C13: CNY | D13: 0.794 | E13: =140000*140% -> 196000 | F13: =260000*140% -> 364000 | G13: =400000*140% -> 560000 | H13: 0.1 | I13: 0.1 | J13: =150*O13 -> 1228.5 | K13: =129*O13 -> 1056.51 | L13: =372*O13 -> 3046.68 | M13: 0.049 | N13: 0.03 | O13: 8.19 | P13: 7.11 | Q13: =Q14*$O$13 -> 65.52 | R13: =R14*$O$13 -> 40.95 | S13: =S14*$O$13 -> 73.71 | T13: =T14*$O$13 -> 16.38 | U13: =U14*$O$13 -> 16.38
A14: France | B14: Euros | C14: EUR | D14: 0.153 | H14: 0.1 | I14: 0.1 | O14: 1 | P14: 0.86 | Q14: 8 | R14: 5 | S14: 9 | T14: 2 | U14: 2
A15: Germany | B15: Euros | C15: EUR | D15: 0.251 | H15: 0.1 | I15: 0.1 | O15: 1 | P15: 0.86 | Q15: =Q14 -> 8 | R15: =R14 -> 5 | S15: =S14 -> 9 | T15: =T14 -> 2 | U15: =U14 -> 2
A16: Hungary | B16: Hungarian Forints | C16: HUF | D16: 92.17 | H16: 0.02 | I16: 0.145 | O16: 381.2 | P16: 328.47
A17: India | B17: Indian Rupees | C17: INR | D17: 10.72 | E17: =430000*126% -> 541800 | F17: =1000000*126% -> 1260000 | G17: =1500000*126% -> 1890000 | H17: 0.15 | I17: 0.1 | J17: 14833.58 | K17: 36681.16 | L17: 1560.6 | M17: 0.125 | N17: 0.14 | O17: 104.27 | P17: 87 | Q17: =$Q$14*$O17 -> 834.16 | R17: =$R$14*$O17 -> 521.35 | S17: =$S$14*$O17 -> 938.43 | T17: =$T$14*$O17 -> 208.54 | U17: =$U$14*$O17 -> 208.54
A18: Indonesia | B18: Indonesian Rupiah | C18: IDR | D18: 1114.74 | H18: 0.25 | I18: 0.1 | O18: 19314.2 | P18: 16665.3 | Q18: =$Q$14*$O18 -> 154513.6 | R18: =$R$14*$O18 -> 96571 | S18: =$S$14*$O18 -> 173827.8 | T18: =$T$14*$O18 -> 38628.4 | U18: =$U$14*$O18 -> 38628.4
A19: Mexico | B19: Mexican Pesos | C19: MXN | D19: 3.972 | H19: 0.1 | I19: 0.05 | O19: 21.26 | P19: 18.32
A20: Pakistan | B20: Pakistani Rupees | C20: PKR | D20: 41.99 | H20: 0.15 | I20: 0.1 | O20: 328.52 | P20: 282.99
A21: Philippines | B21: Philippines Pesos | C21: PHP | D21: 8.847 | E21: =192000*126.5% -> 242880 | F21: =374285*126.5% -> 473470.52 | G21: =425429*126.5% -> 538167.68 | H21: 0.1 | I21: 0.1 | J21: 16240 | K21: 20000 | L21: 3240 | M21: 0.1 | N21: 0.0863 | O21: 67.87 | P21: 58.89 | Q21: =$Q$14*$O21 -> 542.96 | R21: =$R$14*$O21 -> 339.35 | S21: =$S$14*$O21 -> 610.83 | T21: =$T$14*$O21 -> 135.74 | U21: =$U$14*$O21 -> 135.74
A22: South Africa | B22: South African Rand | C22: ZAR | D22: 1.795 | H22: 0.2 | I22: 0.05 | O22: 19.88 | P22: 17.13
A23: Turkey | B23: Turkish Lira | C23: TRY | D23: 4.35 | H23: 0.1 | I23: 0.1 | O23: 49.29 | P23: 42.43
A24: United Kingdom | B24: British Pounds | C24: GBP | D24: 0.346 | E24: 30000 | F24: 43000 | G24: 50000 | H24: 0.18 | I24: 0.03 | O24: 0.88 | P24: 0.76
A25: United States | B25: U.S. Dollars | C25: USD | D25: 0.149 | E25: 70179 | F25: 93567 | G25: 83661 | H25: 0.1 | I25: 0.1 | O25: 1.16 | P25: 1
A26: Vietnam | B26: Vietnamese Dong | C26: VND | D26: 1744 | E26: =105600000*132.5% -> 139920000 | F26: =624273326*132.5% -> 8.2716216e+08 | G26: =695648877*132.5% -> 9.2173476e+08 | H26: 0.1 | I26: 0.1 | J26: =118*O26 -> 3586051.9 | K26: =112*O26 -> 3403710.2 | L26: =180*O26 -> 5470248.6 | M26: 0.059 | N26: 0.062 | O26: 30390.27 | P26: 26369 | Q26: =$Q$14*$O26 -> 243122.16 | R26: =$R$14*$O26 -> 151951.35 | S26: =$S$14*$O26 -> 273512.43 | T26: =$T$14*$O26 -> 60780.54 | U26: =$U$14*$O26 -> 60780.54

Sheet Backup
B2: Facility Area
B3: Details | C3: =Input!C4 -> India | D3: Purpose
B4: IMM Production Hall | C4: =SUMPRODUCT(H20:H60,I20:I60) -> 5.9918916 | D4: Includes gangways & buffer zones
B5: Raw Material Storage | C5: =Conversion!D277 -> 26.435272 | D5: Silo + bag storage, covered with material loaders, fire safety
B6: Finished Goods Warehouse | C6: =Conversion!D293 -> 0.72184792 | D6: 3–5 days buffer stock, stacked pallets, racking possible
B7: CTP Room | C7: =C4*15% -> 0.89878374 | D7: For Pre printing Purpose
B8: QA, Testing & Lab | C8: =C4*1% -> 0.059918916 | D8: QC, testing, documentation
B9: Maintenance + Utility Block | C9: =C4*5% -> 0.29959458 | D9: Compressor, pump room, electrical panels, workshop
B10: Office/Admin Block | C10: =C4*2% -> 0.11983783 | D10: Planning, HR, finance, customer service, etc.
B11: Canteen & Washrooms | C11: =C4*2% -> 0.11983783 | D11: Based on workforce (~150–200 people)
B12: Loading/Unloading Bays | C12: =C4*10% -> 0.59918916 | D12: 5 Bays - Dock-level bays for raw/finished goods
B13: Future Expansion | C13: =C4*25% -> 1.4979729
B14: Total Built Up Area | C14: =SUM(C4:C13) -> 36.744146
B15: FSI | C15: 0.7
B16: Land Area | C16: =C14/C15 -> 52.491638
B18: Machine Details
B19: Details | C19: Machine Model | D19: Cost Per Machine € | E19: Line Speed (Sheets/ Hour) | F19: Power Consumption (KwH) | G19: Hours Utilised | H19: No of Machines Required | I19: Machine Footprint SQM | J19: Area
B20: Printing | C20: KBA 8000 | D20: =8*10^5 -> 800000 | E20: 12000 | F20: 150 | G20: =Conversion!$D$86 -> 47.322396 | H20: =IFERROR(HLOOKUP($C20,Conversion!$D$11:$D$87,ROWS(Conversion!$C$11:$C$87),0),0) -> 0.00597505 | I20: 250 | J20: =H20*I20 -> 1.4937625
B21: Printing | C21: Heidelberg Speedmaster SM 52 | D21: 200000 | E21: 8000 | F21: 150 | G21: =Conversion!$D$86 -> 47.322396 | H21: =IFERROR(HLOOKUP($C21,Conversion!$D$11:$D$87,ROWS(Conversion!$C$11:$C$87),0),0) -> 0 | I21: 250 | J21: =H21*I21 -> 0
B22: Printing | C22: Heidelberg Speedmaster SM 74 / XL 75 | D22: 350000 | E22: 12000 | F22: 150 | G22: =Conversion!$D$86 -> 47.322396 | H22: =IFERROR(HLOOKUP($C22,Conversion!$D$11:$D$87,ROWS(Conversion!$C$11:$C$87),0),0) -> 0 | I22: 250 | J22: =H22*I22 -> 0
B23: Printing | C23: Heidelberg Speedmaster SM 102 / XL 106 | D23: 800000 | E23: 14000 | F23: 150 | G23: =Conversion!$D$86 -> 47.322396 | H23: =IFERROR(HLOOKUP($C23,Conversion!$D$11:$D$87,ROWS(Conversion!$C$11:$C$87),0),0) -> 0 | I23: 250 | J23: =H23*I23 -> 0
B24: Printing | C24: KBA Rapida 75 | D24: 400000 | E24: 10000 | F24: 150 | G24: =Conversion!$D$86 -> 47.322396 | H24: =IFERROR(HLOOKUP($C24,Conversion!$D$11:$D$87,ROWS(Conversion!$C$11:$C$87),0),0) -> 0 | I24: 250 | J24: =H24*I24 -> 0
B25: Printing | C25: KBA Rapida 106 | D25: 750000 | E25: 12000 | F25: 150 | G25: =Conversion!$D$86 -> 47.322396 | H25: =IFERROR(HLOOKUP($C25,Conversion!$D$11:$D$87,ROWS(Conversion!$C$11:$C$87),0),0) -> 0 | I25: 250 | J25: =H25*I25 -> 0
B26: Printing | C26: Komori Lithrone G / GL series | D26: 600000 | E26: 12000 | F26: 150 | G26: =Conversion!$D$86 -> 47.322396 | H26: =IFERROR(HLOOKUP($C26,Conversion!$D$11:$D$87,ROWS(Conversion!$C$11:$C$87),0),0) -> 0 | I26: 250 | J26: =H26*I26 -> 0
B27: Printing | C27: Manroland R700 series | D27: 300000 | E27: 8000 | F27: 150 | G27: =Conversion!$D$86 -> 47.322396 | H27: =IFERROR(HLOOKUP($C27,Conversion!$D$11:$D$87,ROWS(Conversion!$C$11:$C$87),0),0) -> 0 | I27: 250 | J27: =H27*I27 -> 0
B28: Printing | C28: Manroland R900 series | D28: 800000 | E28: 15000 | F28: 150 | G28: =Conversion!$D$86 -> 47.322396 | H28: =IFERROR(HLOOKUP($C28,Conversion!$D$11:$D$87,ROWS(Conversion!$C$11:$C$87),0),0) -> 0 | I28: 250 | J28: =H28*I28 -> 0
B29: Printing | C29: Mitsubishi Diamond / high-quality sheetfed
B31: Spot Varnish | C31: Unison | D31: 120000 | E31: 5000 | F31: 20 | G31: =Conversion!$D$110 -> 0 | H31: =IFERROR(HLOOKUP($C31,Conversion!$D$99:$D$111,ROWS(Conversion!$C$99:$C$111),0),0) -> 0 | I31: 50 | J31: =H31*I31 -> 0
B32: Spot Varnish | C32: MGI JETvarnish 3D | D32: 500000 | E32: 4000 | F32: 20 | G32: =Conversion!$D$110 -> 0 | H32: =IFERROR(HLOOKUP($C32,Conversion!$D$99:$D$111,ROWS(Conversion!$C$99:$C$111),0),0) -> 0 | I32: 50 | J32: =H32*I32 -> 0
B33: Spot Varnish | C33: Scodix Scodix Ultra / Scodix SENSE | D33: 500000 | E33: 4000 | F33: 20 | G33: =Conversion!$D$110 -> 0 | H33: =IFERROR(HLOOKUP($C33,Conversion!$D$99:$D$111,ROWS(Conversion!$C$99:$C$111),0),0) -> 0 | I33: 50 | J33: =H33*I33 -> 0
B34: Spot Varnish | C34: Heidelberg Speedmaster | D34: 150000 | E34: 8000 | F34: 20 | G34: =Conversion!$D$110 -> 0 | H34: =IFERROR(HLOOKUP($C34,Conversion!$D$99:$D$111,ROWS(Conversion!$C$99:$C$111),0),0) -> 0 | I34: 50 | J34: =H34*I34 -> 0
B35: Spot Varnish | C35: Komori | D35: 100000 | E35: 8000 | F35: 20 | G35: =Conversion!$D$110 -> 0 | H35: =IFERROR(HLOOKUP($C35,Conversion!$D$99:$D$111,ROWS(Conversion!$C$99:$C$111),0),0) -> 0 | I35: 50 | J35: =H35*I35 -> 0
B36: Spot Varnish | C36: KBA Rapida | D36: 2,00,000 | E36: 8000 | F36: 20 | G36: =Conversion!$D$110 -> 0 | H36: =IFERROR(HLOOKUP($C36,Conversion!$D$99:$D$111,ROWS(Conversion!$C$99:$C$111),0),0) -> 0 | I36: 50 | J36: =H36*I36 -> 0
B37: Spot Varnish | C37: Bobst | D37: 250000 | E37: =E20*70% -> 8400 | F37: 20 | G37: =Conversion!$D$110 -> 0 | H37: =IFERROR(HLOOKUP($C37,Conversion!$D$99:$D$111,ROWS(Conversion!$C$99:$C$111),0),0) -> 0 | I37: 50 | J37: =H37*I37 -> 0
B39: Hot Foiling | C39: Hot Foil Machine | D39: 250000 | E39: 5000 | F39: 50 | G39: =Conversion!D125 -> 0 | H39: =IFERROR(HLOOKUP($C39,Conversion!$D$114:$D$126,ROWS(Conversion!$C$114:$C$126),0),0) -> 0 | I39: 100 | J39: =H39*I39 -> 0
B41: Lamination | C41: Lamination Machine | D41: 65000 | E41: 5000 | F41: 50 | G41: =Conversion!$D$145 -> 0 | H41: =IFERROR(HLOOKUP($C41,Conversion!$D$135:$D$146,ROWS(Conversion!$C$135:$C$146),0),0) -> 0 | I41: 50 | J41: =H41*I41 -> 0
B42: Lamination | C42: Kompac KwikPrint / EZ Koat | D42: 150000 | E42: 3529.4118 | F42: 20 | G42: =Conversion!$D$145 -> 0 | H42: =IFERROR(HLOOKUP($C42,Conversion!$D$135:$D$146,ROWS(Conversion!$C$135:$C$146),0),0) -> 0 | I42: 50 | J42: =H42*I42 -> 0
B43: Lamination | C43: Billhöfer Eco 66, Eco 76, Eco | D43: 450000 | E43: 7058.8235 | F43: 60 | G43: =Conversion!$D$145 -> 0 | H43: =IFERROR(HLOOKUP($C43,Conversion!$D$135:$D$146,ROWS(Conversion!$C$135:$C$146),0),0) -> 0 | I43: 50 | J43: =H43*I43 -> 0
B44: Lamination | C44: Lamina Lamina Blackline, SA, FA, FA Blackline | D44: 600000 | E44: 9411.7647 | F44: 70 | G44: =Conversion!$D$145 -> 0 | H44: =IFERROR(HLOOKUP($C44,Conversion!$D$135:$D$146,ROWS(Conversion!$C$135:$C$146),0),0) -> 0 | I44: 50 | J44: =H44*I44 -> 0
B45: Lamination | C45: Tunkers Variowell / Sheetmaster | D45: 450000 | E45: 8235.2941 | F45: 50 | G45: =Conversion!$D$145 -> 0 | H45: =IFERROR(HLOOKUP($C45,Conversion!$D$135:$D$146,ROWS(Conversion!$C$135:$C$146),0),0) -> 0 | I45: 50 | J45: =H45*I45 -> 0
B46: Lamination | C46: Billhöfer Wet-Lam series | D46: 400000 | E46: 5294.1176 | F46: 45 | G46: =Conversion!$D$145 -> 0 | H46: =IFERROR(HLOOKUP($C46,Conversion!$D$135:$D$146,ROWS(Conversion!$C$135:$C$146),0),0) -> 0 | I46: 50 | J46: =H46*I46 -> 0
B47: Lamination | C47: JMD Machinery FMZ Series | D47: 90000 | E47: 5294.1176 | F47: 30 | G47: =Conversion!$D$145 -> 0 | H47: =IFERROR(HLOOKUP($C47,Conversion!$D$135:$D$146,ROWS(Conversion!$C$135:$C$146),0),0) -> 0 | I47: 50 | J47: =H47*I47 -> 0
B48: Lamination | C48: Hongming HM Series | D48: 150000 | E48: 7058.8235 | F48: 55 | G48: =Conversion!$D$145 -> 0 | H48: =IFERROR(HLOOKUP($C48,Conversion!$D$135:$D$146,ROWS(Conversion!$C$135:$C$146),0),0) -> 0 | I48: 50 | J48: =H48*I48 -> 0
B49: Lamination | C49: Jiawei JW Series | D49: 100000 | E49: 4705.8824 | F49: 40 | G49: =Conversion!$D$145 -> 0 | H49: =IFERROR(HLOOKUP($C49,Conversion!$D$135:$D$146,ROWS(Conversion!$C$135:$C$146),0),0) -> 0 | I49: 50 | J49: =H49*I49 -> 0
B50: Lamination | C50: Wanlian Machinery WL Series | D50: 80000 | E50: 5882.3529 | F50: 35 | G50: =Conversion!$D$145 -> 0 | H50: =IFERROR(HLOOKUP($C50,Conversion!$D$135:$D$146,ROWS(Conversion!$C$135:$C$146),0),0) -> 0 | I50: 50 | J50: =H50*I50 -> 0
B51: Lamination | C51: Jialite YFML Series | D51: 30000 | E51: 2941.1765 | F51: 20 | G51: =Conversion!$D$145 -> 0 | H51: =IFERROR(HLOOKUP($C51,Conversion!$D$135:$D$146,ROWS(Conversion!$C$135:$C$146),0),0) -> 0 | I51: 50 | J51: =H51*I51 -> 0
B53: Creasing & Blanking | C53: Bobst Mastercut | D53: 700000 | E53: 7500 | F53: 50 | G53: =Conversion!$D$173 -> 59.928333 | H53: =IFERROR(HLOOKUP($C53,Conversion!$D$163:$D$174,ROWS(Conversion!$C$163:$C$174),0),0) -> 0.0075667088 | I53: 250 | J53: =H53*I53 -> 1.8916772
B54: Creasing & Blanking | C54: Masterwork (China) Ecocut 170CS | D54: 150000 | E54: 6000 | F54: 50 | G54: =Conversion!$D$173 -> 59.928333 | H54: =IFERROR(HLOOKUP($C54,Conversion!$D$163:$D$174,ROWS(Conversion!$C$163:$C$174),0),0) -> 0 | I54: 250 | J54: =H54*I54 -> 0
B56: Folder - Gluer | C56: Bobst Masterfold | D56: 600000 | E56: 120000 | F56: 50 | G56: =Conversion!D193 -> 82.572396 | H56: =IFERROR(HLOOKUP($C56,Conversion!$D$183:$D$194,ROWS(Conversion!$C$183:$C$194),0),0) -> 0.010425808 | I56: 250 | J56: =H56*I56 -> 2.6064519
B58: Window Carton | C58: Medium automatic window patcher | D58: 60000 | E58: 1800 | F58: 10 | G58: =Conversion!D159 -> 0 | H58: =Conversion!D160 -> 0 | I58: 15 | J58: =H58*I58 -> 0
B60: Total
B62: List of Ancilliary Equipments
B63: Details | C63: EUR | D63: =Input!A112 -> Euro | E63: =Input!C5 -> INR | F63: Purpose
B64: Chiller System (Centralized) | C64: 3032.5554 | D64: =_xlfn.XLOOKUP($E$151,Input!$A$112:$A$113,Input!$C$112:$C$113) -> 104.27 | E64: =D64*C64 -> 316204.55 | F64: 900–1000 TR with piping, pumps, tanks
B65: Air Compressors & Air Network | C65: 1299.6666 | D65: =_xlfn.XLOOKUP($E$151,Input!$A$112:$A$113,Input!$C$112:$C$113) -> 104.27 | E65: =D65*C65 -> 135516.24 | F65: 3–4 screw compressors (100 HP each), dryers, receivers
B66: Mould Temperature Controllers (MTC) | C66: 21.66111 | D66: =_xlfn.XLOOKUP($E$151,Input!$A$112:$A$113,Input!$C$112:$C$113) -> 104.27 | E66: =D66*C66 -> 2258.6039 | F66: 1 per machine, 12–24 kW
B67: Material Dryers & Dehumidifiers | C67: 36.10185 | D67: =_xlfn.XLOOKUP($E$151,Input!$A$112:$A$113,Input!$C$112:$C$113) -> 104.27 | E67: =D67*C67 -> 3764.3399 | F67: 1 per machine
B68: Chilled Water Storage Tanks & Pumps | C68: 475.36589 | D68: =_xlfn.XLOOKUP($E$151,Input!$A$112:$A$113,Input!$C$112:$C$113) -> 104.27 | E68: =D68*C68 -> 49566.401 | F68: 50–60 m³ + pump skid
B69: ETP/STP Plant (50–75 KLD) | C69: 858.61238 | D69: =_xlfn.XLOOKUP($E$151,Input!$A$112:$A$113,Input!$C$112:$C$113) -> 104.27 | E69: =D69*C69 -> 89527.513 | F69: Water treatment + neutralization + reuse
B70: DG Sets (2 × 750 kVA) | C70: 1723.9379 | D70: =_xlfn.XLOOKUP($E$151,Input!$A$112:$A$113,Input!$C$112:$C$113) -> 104.27 | E70: =D70*C70 -> 179755.01 | F70: Diesel gensets with AMF & cabling
B71: Electrical Infrastructure (Transformers, Panels) | C71: 2435.5322 | D71: =_xlfn.XLOOKUP($E$151,Input!$A$112:$A$113,Input!$C$112:$C$113) -> 104.27 | E71: =D71*C71 -> 253952.95 | F71: 3 MW load, panels, busbars, cabling
B72: Material Handling (Conveyors, Cranes, Trolleys) | C72: 1181.5151 | D72: =_xlfn.XLOOKUP($E$151,Input!$A$112:$A$113,Input!$C$112:$C$113) -> 104.27 | E72: =D72*C72 -> 123196.58 | F72: 5 T overhead + 3 T gantry + pallet handling
B73: Tool Room & Maintenance Setup | C73: 1474.6561 | D73: =_xlfn.XLOOKUP($E$151,Input!$A$112:$A$113,Input!$C$112:$C$113) -> 104.27 | E73: =D73*C73 -> 153762.4 | F73: Lathe, grinder, polishing, hydraulic press, tool benches
B74: QA & Lab Equipment | C74: 648.49067 | D74: =_xlfn.XLOOKUP($E$151,Input!$A$112:$A$113,Input!$C$112:$C$113) -> 104.27 | E74: =D74*C74 -> 67618.122 | F74: Moisture analyzer, colorimeter, tensile tester, etc.
B75: Firefighting & Safety Systems | C75: 723.52881 | D75: =_xlfn.XLOOKUP($E$151,Input!$A$112:$A$113,Input!$C$112:$C$113) -> 104.27 | E75: =D75*C75 -> 75442.349 | F75: Hydrant + extinguishers + sprinklers + sensors
... B77: Miscellaneous & Installation | C77: 1456.0115 | D77: =_xlfn.XLOOKUP($E$151,Input!$A$112:$A$113,Input!$C$112:$C$113) -> 104.27 | E77: =D77*C77 -> 151818.32 | F77: Cabling, supports, commissioning, etc. (≈10%)
B78: Contigencies | C78: =SUM(C64:C77)*10% -> 1601.6126 | D78: =_xlfn.XLOOKUP($E$151,Input!$A$112:$A$113,Input!$C$112:$C$113) -> 104.27 | E78: =D78*C78 -> 167000.15 | F78: ~ 10%
B79: Auxiliary Equipment | C79: =SUM(C64:C78) -> 17617.739 | E79: =SUM(E64:E78) -> 1837001.6
B82: Type of Container | C82: Euro Pallet - Single Stack | D82: Euro Pallet - Double Stack | E82: Standard Pallet - Single Stack | F82: Standard Pallet - Double Stack
B83: 19 Feet | C83: 8 | D83: =C83*2 -> 16 | E83: 8 | F83: 16
B84: 22 feet / 24 feet | C84: 11 | D84: =C84*2 -> 22 | E84: 10 | F84: 20
B85: 26 feet | C85: 11 | D85: =C85*2 -> 22 | E85: 10 | F85: 20
B86: 32 feet | C86: 14 | D86: =C86*2 -> 28 | E86: 12 | F86: 24
B87: 20 Feet Container | C87: 11 | D87: =C87*2 -> 22 | E87: 10 | F87: 20
B88: 40 Feet Container | C88: 24 | D88: =C88*2 -> 48 | E88: 21 | F88: 42
B90: Type of Pallet
B91: Euro Pallet - Single Stack
B92: Euro Pallet - Double Stack
B93: Standard Pallet - Single Stack
B94: Standard Pallet - Double Stack
B96: Machine Type | C96: No of Colours | D96: Mach+Col | E96: Changeover time (min) | F96: Time required for Registration & Shade matching (mins)
B97: Offset | C97: 1 | D97: =B97&C97 -> Offset1 | E97: 15 | F97: 6
B98: Offset | C98: 2 | D98: =B98&C98 -> Offset2 | E98: 25 | F98: 10
B99: Offset | C99: 3 | D99: =B99&C99 -> Offset3 | E99: 35 | F99: 14
B100: Offset | C100: 4 | D100: =B100&C100 -> Offset4 | E100: 45 | F100: 15
B101: Offset | C101: 5 | D101: =B101&C101 -> Offset5 | E101: 45 | F101: 15
B102: Offset | C102: 6 | D102: =B102&C102 -> Offset6 | E102: 45 | F102: 15
B103: Offset | C103: 7 | D103: =B103&C103 -> Offset7 | E103: 45 | F103: 15
B104: Offset | C104: 8 | D104: =B104&C104 -> Offset8 | E104: 45 | F104: 15
B105: Offset | C105: 9 | D105: =B105&C105 -> Offset9 | E105: 45 | F105: 15
B106: Offset | C106: 10 | D106: =B106&C106 -> Offset10 | E106: 45 | F106: 15
B107: Offset | C107: 11 | D107: =B107&C107 -> Offset11 | E107: 45 | F107: 15
B108: Offset | C108: 12 | D108: =B108&C108 -> Offset12 | E108: 45 | F108: 15
B109: Bob St | E109: 30
B110: Bob St | E110: 30
B116: Printing Type | C116: Max Width | D116: Max Length
B117: IIIB | C117: 1020 | D117: 720
B118: VI | C118: 1420 | D118: 1020
B119: VIB | C119: 1450 | D119: 1020
B122: Grain Direction
...
